netlink/sharepoint/base/__init__.py
netlink/sharepoint/base/_item.py
netlink/sharepoint/base/_list.py
netlink/sharepoint/base/_site.py
netlink/sharepoint/base/classes.puml
netlink/sharepoint/base/cli.py
netlink_sharepoint_base-0.0.8.dist-info/entry_points.txt
netlink_sharepoint_base-0.0.8.dist-info/WHEEL
netlink_sharepoint_base-0.0.8.dist-info/METADATA
netlink_sharepoint_base-0.0.8.dist-info/RECORD
