Metadata-Version: 2.1
Name: netlink-sharepoint-base
Version: 0.0.8
Summary: Basic Tools for interaction with Sharepoint Sites
Home-page: https://gitlab.com/netlink_python/netlink-sharepoint-base
License: MIT
Keywords: sharepoint
Author: Bernhard Radermacher
Author-email: bernhard.radermacher@netlink-consulting.com
Requires-Python: >=3.8,<=3.12
Classifier: License :: OSI Approved :: MIT License
Classifier: Programming Language :: Python :: 3
Classifier: Programming Language :: Python :: 3.10
Classifier: Programming Language :: Python :: 3.8
Classifier: Programming Language :: Python :: 3.9
Classifier: Topic :: Software Development
Requires-Dist: Office365-REST-Python-Client (>=2.5.9)
Requires-Dist: click (>=8.1.3)
Requires-Dist: netlink-logging (>=0.1.15)
Project-URL: Repository, https://gitlab.com/netlink_python/netlink-sharepoint-base
